{
  "fields": [
    "KS1",
    "KS2",
    "Rasen"
  ],
  "montag": [
    {
      "field": "Rasen",
      "name": "Platzsperre",
      "type": "sperre",
      "time": "Dezember - Februar",
      "kabine": "",
      "position": "ganz"
    },
    {
      "field": "KS1",
      "name": "E1w",
      "type": "weibliche-jugend",
      "time": "17:30 - 19:00",
      "kabine": "Kabine X",
      "position": "oben-links"
    },
    {
      "field": "KS1",
      "name": "B1w",
      "type": "weibliche-jugend",
      "time": "18:00 - 19:30",
      "kabine": "Kabine X",
      "position": "oben-rechts"
    },
    {
      "field": "KS2",
      "name": "C1w",
      "type": "weibliche-jugend",
      "time": "18:00 - 19:30",
      "kabine": "Kabine X",
      "position": "unten-links"
    },
    {
      "field": "ks2",
      "name": "D1w",
      "type": "weibliche-jugend",
      "time": "17:30 - 19:00",
      "kabine": "Kabine X",
      "position": "unten-rechts"
    },
    {
      "field": "KS2",
      "name": "D2",
      "type": "maennliche-jugend",
      "time": "17:00 - 18:30",
      "kabine": "Kabine X",
      "position": "oben-links"
    },
    {
      "field": "KS2",
      "name": "E1",
      "type": "maennliche-jugend",
      "time": "17:00 - 18:30",
      "kabine": "Kabine X",
      "position": "oben-rechts"
    },
    {
      "field": "KS2",
      "name": "D3",
      "type": "maennliche-jugend",
      "time": "17:30 - 19:00",
      "kabine": "Kabine X",
      "position": "unten-links"
    },
    {
      "field": "KS2",
      "name": "E4",
      "type": "maennliche-jugend",
      "time": "17:00 - 18:30",
      "kabine": "Kabine X",
      "position": "unten-rechts"
    },
    {
      "field": "KS2",
      "name": "Damen Irish Rover",
      "type": "frauen",
      "time": "19:00 - 21:00",
      "kabine": "Kabine X",
      "position": "mittig"
    }
  ]
}
